prowl/__init__.py
prowl/__main__.py
prowl/defaults.py
prowl/main.py
prowl/mappers.py
prowl/models.py
prowl/tools.py
prowl/types.py
prowl-0.3.0.dist-info/licenses/LICENSE
prowl-0.3.0.dist-info/METADATA
prowl-0.3.0.dist-info/WHEEL
prowl-0.3.0.dist-info/top_level.txt
prowl-0.3.0.dist-info/RECORD
