Metadata-Version: 2.4
Name: prowl
Version: 0.3.0
Summary: Generate caracal/caracat/saimiris probes and build awesome probing tools.
Requires-Python: >=3.13
License-File: LICENSE
Requires-Dist: pygfc>=1.1.0
Provides-Extra: cli
Requires-Dist: typer>=0.15.2; extra == "cli"
Dynamic: license-file
